medimage/__init__.py
medimage/io_avsfield.py
medimage/io_dicom.py
medimage/io_metaimage.py
medimage/ops_mask.py
medimage/ops_math.py
medimage-1.0.7.dist-info/LICENSE
medimage-1.0.7.dist-info/METADATA
medimage-1.0.7.dist-info/WHEEL
medimage-1.0.7.dist-info/top_level.txt
medimage-1.0.7.dist-info/RECORD
