Metadata-Version: 2.1
Name: medimage
Version: 1.0.7
Summary: Represent medical images as numpy array. Supported: .mhd (R/W),.xdr (R/W), dicom (R). Pure Python.
Home-page: https://github.com/brenthuisman/medimage
Author: Brent Huisman
Author-email: mail@brenthuisman.net
License: LGPL
Keywords: medical image xdr mhd dicom numpy
Platform: UNKNOWN
Classifier: Development Status :: 5 - Production/Stable
Classifier: Programming Language :: Python :: 3
Classifier: Operating System :: OS Independent
Classifier: License :: OSI Approved :: GNU Lesser General Public License v3 or later (LGPLv3+)
Classifier: Topic :: Scientific/Engineering :: Medical Science Apps.
Classifier: Topic :: Scientific/Engineering :: Physics
Classifier: Intended Audience :: Science/Research
Classifier: Intended Audience :: Healthcare Industry
Requires-Dist: numpy
Requires-Dist: pydicom
